httpsig_cffi/__init__.py
httpsig_cffi/_version.py
httpsig_cffi/requests_auth.py
httpsig_cffi/sign.py
httpsig_cffi/utils.py
httpsig_cffi/verify.py
httpsig_cffi/tests/__init__.py
httpsig_cffi/tests/rsa_private.pem
httpsig_cffi/tests/rsa_public.pem
httpsig_cffi/tests/test_signature.py
httpsig_cffi/tests/test_utils.py
httpsig_cffi/tests/test_verify.py
httpsig_cffi-15.0.0.dist-info/DESCRIPTION.rst
httpsig_cffi-15.0.0.dist-info/METADATA
httpsig_cffi-15.0.0.dist-info/metadata.json
httpsig_cffi-15.0.0.dist-info/RECORD
httpsig_cffi-15.0.0.dist-info/top_level.txt
httpsig_cffi-15.0.0.dist-info/WHEEL
httpsig_cffi-15.0.0.dist-info/zip-safe
