Metadata-Version: 1.1
Name: httpsig_cffi
Version: 15.0.0
Summary: Secure HTTP request signing using the HTTP Signature draft specification
Home-page: https://github.com/hawkowl/httpsig_cffi
Author: HawkOwl
Author-email: hawkowl@atleastfornow.net
License: MIT
Keywords: http,authorization,api,web
Platform: UNKNOWN
Classifier: Development Status :: 5 - Production/Stable
Classifier: Environment :: Web Environment
Classifier: Intended Audience :: Developers
Classifier: License :: OSI Approved :: MIT License
Classifier: Operating System :: OS Independent
Classifier: Programming Language :: Python
Classifier: Programming Language :: Python :: 2.7
Classifier: Programming Language :: Python :: 3.2
Classifier: Programming Language :: Python :: 3.3
Classifier: Programming Language :: Python :: 3.4
Classifier: Topic :: Internet :: WWW/HTTP
Classifier: Topic :: Software Development :: Libraries :: Python Modules
